Workbook

Sheet Overview
A1: Create a brand report for Brand ABC.
A3: 1 | B3: Year-on-Year (YOY) Sales Performance 2017-2022; show average order value (AOV)
A4: 2 | B4: Year-to-Date (YTD) Sales Performance for the year 2022 only on a monthly basis from January-October; Show average order value (AOV) per month
A5: 3 | B5: Performance per Store Location (total sales generated, total number of transactions, and unique customer count)
A6: 4 | B6: Top 3 SKUs/items based on total sales generated and units sold
A7: 5 | B7: Shopper Profile / Demographics: age group (i.e. 20s, 30s, 40s, and so on), gender split (% Male-Female), day of the week customers usually shop, which store locations they usually shop; top selling SKU/item based on total sales generated; show count of members with mobile number and with email address
A8: 6 | B8: Determine CRM segment per customer. Show breakdown based on counts.
B9: a | C9: Loyal: with 3 or more visits, with last visit in the past 12 months
B10: b | C10: Engaged: with 2 visits, with last visit in the past 12 months
B11: c | C11: New acqui: with 1 visit in the past 6 months
B12: d | C12: One timers: with 1 visit 7 to 12 months ago
B13: e | C13: Lapsers: last visit between 13 to 24 months ago
B14: f | C14: Sleepers: last visit between 25 to 36 months ago
B15: g | C15: Churned: last visit >= 36 months
B16: h | C16: Lead only: No visit
A17: 7 | B17: Insights and recommendation

Sheet Customer Base
A1: Brand ABC Customer Base
A2: Data as of October 31, 2022
A4: Customer Number | B4: Registration Date | C4: Registration Year | D4: Gender | E4: BirthDate | F4: MobileNo | G4: EmailAdd
A5: 100234 | B5: 20150213 | C5: =LEFT(B5,4) -> 2015 | D5: F | E5: 0 | F5: 639391420224 | G5: NULL
A6: 124503 | B6: 20170111 | C6: =LEFT(B6,4) -> 2017 | D6: M | E6: 0 | F6: 639221840865 | G6: NULL
A7: 236492 | B7: 20210921 | C7: =LEFT(B7,4) -> 2021 | D7: F | E7: 0 | F7: 639771345236 | G7: NULL
A8: 387943 | B8: 20151114 | C8: =LEFT(B8,4) -> 2015 | D8: F | E8: 19860614 | F8: 0 | G8: sampleonly10@gmail.com
A9: 456072 | B9: 20181017 | C9: =LEFT(B9,4) -> 2018 | D9: M | E9: 19751402 | F9: 639031422959 | G9: sampleonly11@gmail.com
A10: 553583 | B10: 20141202 | C10: =LEFT(B10,4) -> 2014 | D10: NULL | E10: 0 | F10: 639221385465 | G10: sampleonly12@yahoo.com
A11: 651095 | B11: 20150401 | C11: =LEFT(B11,4) -> 2015 | D11: NULL | E11: 19790429 | F11: 0 | G11: sampleonly13@yahoo.com
A12: 748606 | B12: 20201220 | C12: =LEFT(B12,4) -> 2020 | D12: M | E12: 19760925 | F12: 0 | G12: sampleonly14@gmail.com
A13: 846118 | B13: 20170510 | C13: =LEFT(B13,4) -> 2017 | D13: F | E13: 19890809 | F13: 0 | G13: sampleonly15@gmail.com
A14: 943630 | B14: 20140830 | C14: =LEFT(B14,4) -> 2014 | D14: F | E14: 0 | F14: 6.3998124e+11 | G14: NULL
A15: 345424 | B15: 20210121 | C15: =LEFT(B15,4) -> 2021 | D15: M | E15: 0 | F15: 6.391712e+11 | G15: NULL
A16: 380383 | B16: 20150606 | C16: =LEFT(B16,4) -> 2015 | D16: F | E16: 0 | F16: 0 | G16: sampleonly18@yahoo.com
... A104: 553256 | B104: 20220911 | C104: =LEFT(B104,4) -> 2022 | D104: M | E104: 19731214 | F104: 0 | G104: sampleonly106@yahoo.com.ph

Sheet Clean_Customer Base
